dendrify/__init__.py
dendrify/compartment.py
dendrify/ephysproperties.py
dendrify/equations.py
dendrify/neuronmodel.py
dendrify/playground.py
dendrify/utils.py
dendrify/version.py
dendrify-2.2.0.dist-info/LICENSE
dendrify-2.2.0.dist-info/METADATA
dendrify-2.2.0.dist-info/WHEEL
dendrify-2.2.0.dist-info/top_level.txt
dendrify-2.2.0.dist-info/RECORD
