Metadata-Version: 2.2
Name: dendrify
Version: 2.2.0
Summary: A package for adding dendrites to SNNs
Author: Michalis Pagkalos
Author-email: <mpagkalos93@gmail.com>
Project-URL: Documentation, https://dendrify.readthedocs.io/en/latest/
Project-URL: Source, https://github.com/Poirazi-Lab/dendrify
Project-URL: Tracker, https://github.com/Poirazi-Lab/dendrify/issues
Keywords: python,brian2,dendrites,SNNs,network models
Classifier: Development Status :: 5 - Production/Stable
Classifier: Intended Audience :: Science/Research
Classifier: Programming Language :: Python :: 3
Classifier: Operating System :: OS Independent
Classifier: Topic :: Scientific/Engineering :: Bio-Informatics
License-File: LICENSE
Requires-Dist: brian2
Requires-Dist: matplotlib
Requires-Dist: networkx
Dynamic: author
Dynamic: author-email
Dynamic: classifier
Dynamic: description
Dynamic: description-content-type
Dynamic: keywords
Dynamic: project-url
Dynamic: requires-dist
Dynamic: summary
